README.rst
setup.py
arcadeplus/__init__.py
arcadeplus/application.py
arcadeplus/arcade_types.py
arcadeplus/buffered_draw_commands.py
arcadeplus/draw_commands.py
arcadeplus/drawing_support.py
arcadeplus/earclip_module.py
arcadeplus/emitter.py
arcadeplus/emitter_simple.py
arcadeplus/geometry.py
arcadeplus/gui.py
arcadeplus/isometric.py
arcadeplus/joysticks.py
arcadeplus/particle.py
arcadeplus/physics_engines.py
arcadeplus/py.typed
arcadeplus/read_tiled_map.py
arcadeplus/shader.py
arcadeplus/sound.py
arcadeplus/sprite.py
arcadeplus/sprite_list.py
arcadeplus/text.py
arcadeplus/texture.py
arcadeplus/tilemap.py
arcadeplus/utils.py
arcadeplus/version.py
arcadeplus/window_commands.py
arcadeplus.egg-info/PKG-INFO
arcadeplus.egg-info/SOURCES.txt
arcadeplus.egg-info/dependency_links.txt
arcadeplus.egg-info/requires.txt
arcadeplus.egg-info/top_level.txt
arcadeplus/color/__init__.py
arcadeplus/csscolor/__init__.py
arcadeplus/examples/__init__.py
arcadeplus/examples/array_backed_grid.py
arcadeplus/examples/array_backed_grid_buffered.py
arcadeplus/examples/asteroid_smasher.py
arcadeplus/examples/bouncing_ball.py
arcadeplus/examples/bouncing_balls.py
arcadeplus/examples/bouncing_rectangle.py
arcadeplus/examples/decorator_drawing_example.py
arcadeplus/examples/drawing_primitives.py
arcadeplus/examples/drawing_text.py
arcadeplus/examples/drawing_with_functions.py
arcadeplus/examples/drawing_with_loops.py
arcadeplus/examples/dual_stick_shooter.py
arcadeplus/examples/frametime_plotter.py
arcadeplus/examples/full_screen_example.py
arcadeplus/examples/gradients.py
arcadeplus/examples/gui_button.py
arcadeplus/examples/gui_dialogue_box.py
arcadeplus/examples/gui_text_box.py
arcadeplus/examples/gui_text_button.py
arcadeplus/examples/happy_face.py
arcadeplus/examples/isometric_example.py
arcadeplus/examples/joystick.py
arcadeplus/examples/lines_buffered.py
arcadeplus/examples/maze_depth_first.py
arcadeplus/examples/maze_recursive.py
arcadeplus/examples/mountains_midpoint_displacement.py
arcadeplus/examples/mountains_random_walk.py
arcadeplus/examples/move_joystick.py
arcadeplus/examples/move_keyboard.py
arcadeplus/examples/move_mouse.py
