Metadata-Version: 1.2
Name: arcadeplus
Version: 0.6.2
Summary: ArcadePlus Graphics Library
Home-page: https://github.com/GeorgeShao/arcadeplus
Author: George Shao
Author-email: georgeshao123@gmail.com
License: gpl-3.0
Download-URL: https://github.com/GeorgeShao/arcadeplus/archive/0.6.2.tar.gz
Platform: UNKNOWN
Classifier: Development Status :: 4 - Beta
Classifier: Intended Audience :: Developers
Classifier: License :: OSI Approved :: GNU General Public License v3 (GPLv3)
Classifier: Operating System :: OS Independent
Classifier: Programming Language :: Python
Classifier: Programming Language :: Python :: 3.6
Classifier: Programming Language :: Python :: 3.7
Classifier: Programming Language :: Python :: 3.8
Classifier: Programming Language :: Python :: Implementation :: CPython
Classifier: Topic :: Software Development :: Libraries :: Python Modules
Requires-Python: >=3.6
